fastapi_view/__init__.py
fastapi_view/config.py
fastapi_view/view.py
fastapi_view/inertia/__init__.py
fastapi_view/inertia/config.py
fastapi_view/inertia/enums.py
fastapi_view/inertia/inertia.py
fastapi_view/inertia/props.py
fastapi_view/vite/__init__.py
fastapi_view/vite/config.py
fastapi_view/vite/extension.py
fastapi_view-0.6.3.dist-info/METADATA
fastapi_view-0.6.3.dist-info/WHEEL
fastapi_view-0.6.3.dist-info/entry_points.txt
fastapi_view-0.6.3.dist-info/licenses/LICENSE
fastapi_view-0.6.3.dist-info/RECORD
