Metadata-Version: 2.4
Name: fastapi-view
Version: 0.6.3
Summary: A jinja2 view template helping function for FastAPI.
Project-URL: Homepage, https://github.com/turisesonia/fastapi-view.git
Project-URL: Repository, https://github.com/turisesonia/fastapi-view.git
Project-URL: Issues, https://github.com/turisesonia/fastapi-view/issues
Author-email: Sam Yao <turisesonia@gmail.com>
License: MIT
License-File: LICENSE
Keywords: Fastapi,jinja2,template,view
Classifier: Development Status :: 4 - Beta
Classifier: Framework :: FastAPI
Classifier: Intended Audience :: Developers
Classifier: License :: OSI Approved :: MIT License
Classifier: Programming Language :: Python :: 3
Classifier: Programming Language :: Python :: 3.10
Classifier: Programming Language :: Python :: 3.11
Classifier: Programming Language :: Python :: 3.12
Classifier: Topic :: Internet :: WWW/HTTP :: Dynamic Content
Classifier: Topic :: Software Development :: Libraries :: Python Modules
Requires-Python: >=3.10
Requires-Dist: fastapi>=0.70.0
Requires-Dist: jinja2>=3.0.0
Requires-Dist: pydantic-settings>=2.0.0
Provides-Extra: dev
Requires-Dist: faker>=28.0.0; extra == 'dev'
Requires-Dist: fastapi[standard]>=0.115.0; extra == 'dev'
Requires-Dist: httpx>=0.25.1; extra == 'dev'
Requires-Dist: pyquery>=2.0.0; extra == 'dev'
Requires-Dist: pytest-mock>=3.14.0; extra == 'dev'
Requires-Dist: pytest>=7.4.3; extra == 'dev'
Requires-Dist: requests>=2.27.1; extra == 'dev'
Requires-Dist: uvicorn>=0.30.6; extra == 'dev'
